elsabio/__init__.py
elsabio/__main__.py
elsabio/core.py
elsabio/datetime.py
elsabio/exceptions.py
elsabio/log.py
elsabio/metadata.py
elsabio/plugins.py
elsabio/py.typed
elsabio/app/__init__.py
elsabio/app/auth.py
elsabio/app/cli.py
elsabio/app/info.py
elsabio/app/main.py
elsabio/app/resources.py
elsabio/app/_pages/__init__.py
elsabio/app/_pages/home.py
elsabio/app/_pages/init.py
elsabio/app/_pages/sign_in.py
elsabio/app/components/__init__.py
elsabio/app/components/buttons.py
elsabio/app/components/icons.py
elsabio/app/components/sidebar.py
elsabio/app/components/forms/__init__.py
elsabio/app/components/text/__init__.py
elsabio/app/components/text/user_info_text.py
elsabio/app/controllers/__init__.py
elsabio/app/controllers/init.py
elsabio/app/controllers/sign_in.py
elsabio/app/views/__init__.py
elsabio/app/views/init.py
elsabio/cli/__init__.py
elsabio/cli/core.py
elsabio/cli/display.py
elsabio/cli/main.py
elsabio/cli/tariff_analyzer/__init__.py
elsabio/cli/tariff_analyzer/core.py
elsabio/cli/tariff_analyzer/customer_group/__init__.py
elsabio/cli/tariff_analyzer/customer_group/customer_group.py
elsabio/cli/tariff_analyzer/customer_group/map_facilities.py
elsabio/cli/tariff_analyzer/import_/__init__.py
elsabio/cli/tariff_analyzer/import_/core.py
elsabio/cli/tariff_analyzer/import_/facility.py
elsabio/cli/tariff_analyzer/import_/facility_contract.py
elsabio/cli/tariff_analyzer/import_/import_.py
elsabio/cli/tariff_analyzer/import_/meter_data.py
elsabio/cli/tariff_analyzer/import_/product.py
elsabio/config/__init__.py
elsabio/config/config.py
elsabio/config/core.py
elsabio/config/log.py
elsabio/config/tariff_analyzer.py
elsabio/database/__init__.py
elsabio/database/core.py
elsabio/database/init.py
elsabio/database/crud/__init__.py
elsabio/database/crud/serie_type.py
elsabio/database/models/__init__.py
elsabio/database/models/core/__init__.py
elsabio/database/models/core/default.py
elsabio/database/models/core/models.py
elsabio-0.4.0.dist-info/licenses/LICENSE
elsabio-0.4.0.dist-info/METADATA
elsabio-0.4.0.dist-info/WHEEL
elsabio-0.4.0.dist-info/entry_points.txt
elsabio-0.4.0.dist-info/top_level.txt
elsabio-0.4.0.dist-info/RECORD
