Metadata-Version: 2.4
Name: ElSabio
Version: 0.4.0
Summary: The simple electricity meter data analysis platform.
Author-email: Anton Lydell <anton.lydell@tuta.com>
License-Expression: GPL-3.0-or-later
Project-URL: Bug Tracker, https://github.com/antonlydell/ElSabio/issues
Project-URL: Documentation, https://github.com/antonlydell/ElSabio
Project-URL: Source Code, https://github.com/antonlydell/ElSabio
Keywords: Active Power,Adaptable,Apparent Power,Customer Information,Data,Data Analysis,Electricity,Energy,Grid Topology,Meter,Meter Data,Meter Events,Power,Powerful,Reactive Power,Simple,Streamlit,Tariffs,Utility,Visualization,Web
Classifier: Development Status :: 1 - Planning
Classifier: Environment :: Web Environment
Classifier: Intended Audience :: End Users/Desktop
Classifier: Intended Audience :: Other Audience
Classifier: Natural Language :: English
Classifier: Natural Language :: Swedish
Classifier: Operating System :: OS Independent
Classifier: Programming Language :: Python :: 3 :: Only
Classifier: Programming Language :: Python :: 3.12
Classifier: Programming Language :: Python :: 3.13
Classifier: Topic :: Office/Business
Classifier: Topic :: Scientific/Engineering
Requires-Python: >=3.12
License-File: LICENSE
Requires-Dist: click>=8.0
Requires-Dist: duckdb>=1.0
Requires-Dist: pydantic>=2.0
Requires-Dist: pydantic-settings>=2.10
Requires-Dist: streamlit>=1.46
Requires-Dist: streamlit-passwordless>=0.18
Requires-Dist: sqlalchemy>=2.0
Dynamic: license-file
